[
    {
        "Name":  "7zxa.dll",
        "Path":  "D:\\Winrar\\7zxa.dll",
        "Hash":  "8F160B9DA5191F5003CE83D346B5427C",
        "Date":  "30.10.2024_09:49:45"
    },
    {
        "Name":  "CoNowego.txt",
        "Path":  "D:\\Winrar\\CoNowego.txt",
        "Hash":  "03839D9BC2CF40D5CFA459E6ACB61B67",
        "Date":  "30.10.2024_09:49:45"
    },
    {
        "Name":  "CzytajTo.txt",
        "Path":  "D:\\Winrar\\CzytajTo.txt",
        "Hash":  "59AE5C0F732B8D1E2D431C1309973251",
        "Date":  "30.10.2024_09:49:45"
    },
    {
        "Name":  "Default.SFX",
        "Path":  "D:\\Winrar\\Default.SFX",
        "Hash":  "96598ACAE7A6215F7551626CE8EE1313",
        "Date":  "30.10.2024_09:49:45"
    },
    {
        "Name":  "Default64.SFX",
        "Path":  "D:\\Winrar\\Default64.SFX",
        "Hash":  "DE3E08D413260B086073F5BB924ECD08",
        "Date":  "30.10.2024_09:49:45"
    },
    {
        "Name":  "Descript.ion",
        "Path":  "D:\\Winrar\\Descript.ion",
        "Hash":  "7D875432E13F8E5FAD1CDEF6D3EA970E",
        "Date":  "30.10.2024_09:49:45"
    },
    {
        "Name":  "Licencja.txt",
        "Path":  "D:\\Winrar\\Licencja.txt",
        "Hash":  "316225356C408025803DA7FDDD4F6273",
        "Date":  "30.10.2024_09:49:45"
    },
    {
        "Name":  "Order.htm",
        "Path":  "D:\\Winrar\\Order.htm",
        "Hash":  "97ADA23435ED84D0A3E2DF72760C6013",
        "Date":  "30.10.2024_09:49:45"
    },
    {
        "Name":  "Rar.exe",
        "Path":  "D:\\Winrar\\Rar.exe",
        "Hash":  "E020AB8D7E9DFF16E4D7C7477747B563",
        "Date":  "30.10.2024_09:49:45"
    },
    {
        "Name":  "Rar.txt",
        "Path":  "D:\\Winrar\\Rar.txt",
        "Hash":  "8C6D2CCAFD4CFDFED81C0EBF314CD8FF",
        "Date":  "30.10.2024_09:49:45"
    },
    {
        "Name":  "RarExt.dll",
        "Path":  "D:\\Winrar\\RarExt.dll",
        "Hash":  "DF5AC0D0734C6FB46407C787D8C5B4F8",
        "Date":  "30.10.2024_09:49:45"
    },
    {
        "Name":  "RarExt32.dll",
        "Path":  "D:\\Winrar\\RarExt32.dll",
        "Hash":  "B2E3DB48CA6FAF238A0AD357ADD5408C",
        "Date":  "30.10.2024_09:49:45"
    },
    {
        "Name":  "RarExtInstaller.exe",
        "Path":  "D:\\Winrar\\RarExtInstaller.exe",
        "Hash":  "902BC0E1824D07EF86FB5793B0F959A5",
        "Date":  "30.10.2024_09:49:45"
    },
    {
        "Name":  "RarExtLogo.altform-unplated_targetsize-32.png",
        "Path":  "D:\\Winrar\\RarExtLogo.altform-unplated_targetsize-32.png",
        "Hash":  "85EE643E6B0837849E300B11395422C4",
        "Date":  "30.10.2024_09:49:45"
    },
    {
        "Name":  "RarExtLogo.altform-unplated_targetsize-48.png",
        "Path":  "D:\\Winrar\\RarExtLogo.altform-unplated_targetsize-48.png",
        "Hash":  "EC177CBE676473543E8C9B5D9FB0B797",
        "Date":  "30.10.2024_09:49:45"
    },
    {
        "Name":  "RarExtLogo.altform-unplated_targetsize-64.png",
        "Path":  "D:\\Winrar\\RarExtLogo.altform-unplated_targetsize-64.png",
        "Hash":  "248FA2B659874A14B43B5E0E17AC1CFF",
        "Date":  "30.10.2024_09:49:45"
    },
    {
        "Name":  "RarExtPackage.msix",
        "Path":  "D:\\Winrar\\RarExtPackage.msix",
        "Hash":  "FE0CB225CC15061F8B6AB7CC44246C1D",
        "Date":  "30.10.2024_09:49:45"
    },
    {
        "Name":  "RarFiles.lst",
        "Path":  "D:\\Winrar\\RarFiles.lst",
        "Hash":  "1564195C4F4ED7C2D6624B9082D2190F",
        "Date":  "30.10.2024_09:49:45"
    },
    {
        "Name":  "rarnew.dat",
        "Path":  "D:\\Winrar\\rarnew.dat",
        "Hash":  "C69D0B5902A959577C02E9DCDDA77DE0",
        "Date":  "30.10.2024_09:49:45"
    },
    {
        "Name":  "Resources.pri",
        "Path":  "D:\\Winrar\\Resources.pri",
        "Hash":  "43CB15C1F1CC705305AEBA33B0A9EE73",
        "Date":  "30.10.2024_09:49:45"
    },
    {
        "Name":  "Uninstall.exe",
        "Path":  "D:\\Winrar\\Uninstall.exe",
        "Hash":  "722EB1CBBCA73683497110FAD3E3AD33",
        "Date":  "30.10.2024_09:49:45"
    },
    {
        "Name":  "Uninstall.lst",
        "Path":  "D:\\Winrar\\Uninstall.lst",
        "Hash":  "67468BF68034F3ED3EA45503C1D21DBB",
        "Date":  "30.10.2024_09:49:45"
    },
    {
        "Name":  "UnRAR.exe",
        "Path":  "D:\\Winrar\\UnRAR.exe",
        "Hash":  "4658159A70B083D13656DC1CE4C87E2A",
        "Date":  "30.10.2024_09:49:45"
    },
    {
        "Name":  "WinCon.SFX",
        "Path":  "D:\\Winrar\\WinCon.SFX",
        "Hash":  "2CCA304092888BD8215D769D1460A86B",
        "Date":  "30.10.2024_09:49:45"
    },
    {
        "Name":  "WinCon64.SFX",
        "Path":  "D:\\Winrar\\WinCon64.SFX",
        "Hash":  "3EDC78296025877C39A93A92651AD5A7",
        "Date":  "30.10.2024_09:49:45"
    },
    {
        "Name":  "WinRAR.chm",
        "Path":  "D:\\Winrar\\WinRAR.chm",
        "Hash":  "F4BEEA93DEEC3EA28B01D08001B9F23D",
        "Date":  "30.10.2024_09:49:45"
    },
    {
        "Name":  "WinRAR.exe",
        "Path":  "D:\\Winrar\\WinRAR.exe",
        "Hash":  "FDA369875BA4149F10A7C2883D1884E0",
        "Date":  "30.10.2024_09:49:45"
    },
    {
        "Name":  "Zip.SFX",
        "Path":  "D:\\Winrar\\Zip.SFX",
        "Hash":  "4C0174269FBA3084F6AA00FA2F4DDB47",
        "Date":  "30.10.2024_09:49:45"
    },
    {
        "Name":  "Zip64.SFX",
        "Path":  "D:\\Winrar\\Zip64.SFX",
        "Hash":  "D51617C0A2F82C109E100279941B9850",
        "Date":  "30.10.2024_09:49:45"
    },
    {
        "Name":  "zipnew.dat",
        "Path":  "D:\\Winrar\\zipnew.dat",
        "Hash":  "76CDB2BAD9582D23C1F6F4D868218D6C",
        "Date":  "30.10.2024_09:49:45"
    }
]
